{
  "session_id": "session_013",
  "status": "completed",
  "date": "2026-06-16",
  "task": "T-207 \u2014 upgrade Money_Assistance harness 2026-06-15 \u2192 current (2026-06-16) via Implement/09_migration.md (M0-M5); fixed stale source VERSION stamp first",
  "task_ids": [
    "T-207"
  ],
  "skill": "harness_editor",
  "files_changed": [
    ".sessions/active_thread.md",
    ".sessions/gather_complete.md",
    ".sessions/mece_plan.md",
    ".sessions/session_context_cache.md",
    ".sessions/session_tokens.md",
    ".sessions/token_log.jsonl",
    "docs/master_roadmap.md"
  ],
  "summary_context": "T-207 \u2014 upgrade Money_Assistance harness 2026-06-15 \u2192 current (2026-06-16) via Implement/09_migration.md (M0-M5); fixed stale source VERSION stamp first"
}
